LICENSE.txt
MANIFEST.in
README.md
setup.cfg
setup.py
iso4217parse/__init__.py
iso4217parse/data.json
iso4217parse/symbols.json
iso4217parse.egg-info/PKG-INFO
iso4217parse.egg-info/SOURCES.txt
iso4217parse.egg-info/dependency_links.txt
iso4217parse.egg-info/top_level.txt