Metadata-Version: 1.1
Name: iso4217parse
Version: 0.2
Summary: Parse currencies (symbols and codes) from and to ISO4217.
Home-page: https://github.com/tammoippen/iso4217parse
Author: Tammo Ippen
Author-email: tammo.ippen@posteo.de
License: MIT
Download-URL: https://github.com/tammoippen/iso4217parse/archive/v0.2.tar.gz
Platform: UNKNOWN
Classifier: License :: OSI Approved :: MIT License
Classifier: Programming Language :: Python
Classifier: Programming Language :: Python :: 2.7
Classifier: Programming Language :: Python :: 3
Classifier: Programming Language :: Python :: 3.5
Classifier: Programming Language :: Python :: 3.6
Classifier: Programming Language :: Python :: Implementation :: CPython
Classifier: Programming Language :: Python :: Implementation :: PyPy
